pyprompt/__init__.py
pyprompt/allocators/__init__.py
pyprompt/allocators/allocator.py
pyprompt/allocators/trees.py
pyprompt/blocks/__init__.py
pyprompt/blocks/block.py
pyprompt/blocks/chop_block.py
pyprompt/blocks/context_block.py
pyprompt/blocks/messages_block.py
pyprompt/blocks/tools_block.py
pyprompt/builders/__init__.py
pyprompt/builders/builder.py
pyprompt/builders/trees.py
pyprompt/common/__init__.py
pyprompt/common/json.py
pyprompt/common/messages.py
pyprompt/common/tools.py
pyprompt/tokenizers/__init__.py
pyprompt/tokenizers/tiktoken_tokenizer.py
pyprompt/tokenizers/tokenizer.py
pyprompt-0.1.0.dist-info/LICENSE
pyprompt-0.1.0.dist-info/METADATA
pyprompt-0.1.0.dist-info/WHEEL
pyprompt-0.1.0.dist-info/RECORD
