Metadata-Version: 2.1
Name: pyprompt
Version: 0.1.0
Summary: Validation for LLM prompts.
License: MIT
Author: Chris Vincens
Author-email: chrisv@buildwithlayer.com
Requires-Python: >=3.10,<4.0
Classifier: License :: OSI Approved :: MIT License
Classifier: Programming Language :: Python :: 3
Classifier: Programming Language :: Python :: 3.10
Classifier: Programming Language :: Python :: 3.11
Classifier: Programming Language :: Python :: 3.12
Requires-Dist: pytest (>=8.0.0,<9.0.0)
Requires-Dist: tiktoken (>=0.5.2,<0.6.0)
